setup.py
framgia_ci.egg-info/PKG-INFO
framgia_ci.egg-info/SOURCES.txt
framgia_ci.egg-info/dependency_links.txt
framgia_ci.egg-info/entry_points.txt
framgia_ci.egg-info/requires.txt
framgia_ci.egg-info/top_level.txt
framgiaci/__init__.py
framgiaci/common.py
framgiaci/index.py
framgiaci/report_app.py
framgiaci/templates
framgiaci/version.py
framgiaci/commands/__init__.py
framgiaci/commands/check_config.py
framgiaci/commands/init_template.py
framgiaci/commands/run_all.py
framgiaci/commands/run_finish.py
framgiaci/commands/run_notify.py
framgiaci/commands/run_report.py
framgiaci/commands/run_test.py
framgiaci/commands/run_upload.py
framgiaci/commands/show_config.py
framgiaci/commands/test_connect.py
framgiaci/templates/android.yml
framgiaci/templates/ios.yml
framgiaci/templates/php.yml
framgiaci/templates/ruby.yml