Metadata-Version: 1.1
Name: framgia-ci
Version: 0.2.0
Summary: Command Line Tool for Framgia CI service written in Python
Home-page: http://ci-reports.framgia.vn
Author: ThangTD and TienNA @Framgia Vietnam CI/CD Team
Author-email: tran.duc.thang@framgia.com
License: UNKNOWN
Keywords: setuptools development framgia-ci
Platform: UNKNOWN
Classifier: Development Status :: 5 - Production/Stable
Classifier: Intended Audience :: Developers
Classifier: Topic :: Software Development :: Build Tools
Classifier: License :: OSI Approved :: MIT License
Classifier: Programming Language :: Python :: 3.5
